setup.py
preg/__init__.py
preg.egg-info/PKG-INFO
preg.egg-info/SOURCES.txt
preg.egg-info/dependency_links.txt
preg.egg-info/top_level.txt