Metadata-Version: 1.0
Name: preg
Version: 0.11
Summary: Python-customisable grep-like command-line searcher.
Home-page: UNKNOWN
Author: Andrew Magee
Author-email: amagee@gmail.com
License: GPL
Platform: UNKNOWN
